{
	"configurations" : 
	[
		{
			"directories" : 
			[
				{
					"build" : ".",
					"childIndexes" : 
					[
						1
					],
					"hasInstallRule" : true,
					"jsonFile" : "directory-.-Debug-d0094a50bb2071803777.json",
					"minimumCMakeVersion" : 
					{
						"string" : "3.26"
					},
					"projectIndex" : 0,
					"source" : ".",
					"targetIndexes" : 
					[
						0,
						1
					]
				},
				{
					"build" : "_deps/fmt-build",
					"hasInstallRule" : true,
					"jsonFile" : "directory-_deps.fmt-build-Debug-f725dc12fa5412c2e9fc.json",
					"minimumCMakeVersion" : 
					{
						"string" : "3.8"
					},
					"parentIndex" : 0,
					"projectIndex" : 1,
					"source" : "cmake-build-debug/_deps/fmt-src",
					"targetIndexes" : 
					[
						2
					]
				}
			],
			"name" : "Debug",
			"projects" : 
			[
				{
					"childIndexes" : 
					[
						1
					],
					"directoryIndexes" : 
					[
						0
					],
					"name" : "FinalStudyMpi",
					"targetIndexes" : 
					[
						0,
						1
					]
				},
				{
					"directoryIndexes" : 
					[
						1
					],
					"name" : "FMT",
					"parentIndex" : 0,
					"targetIndexes" : 
					[
						2
					]
				}
			],
			"targets" : 
			[
				{
					"directoryIndex" : 0,
					"id" : "FinalS::@6890427a1f51a3e7e1df",
					"jsonFile" : "target-FinalS-Debug-27911338ef93dc160331.json",
					"name" : "FinalS",
					"projectIndex" : 0
				},
				{
					"directoryIndex" : 0,
					"id" : "correcionPrueba::@6890427a1f51a3e7e1df",
					"jsonFile" : "target-correcionPrueba-Debug-9d72f10233b9d69437c5.json",
					"name" : "correcionPrueba",
					"projectIndex" : 0
				},
				{
					"directoryIndex" : 1,
					"id" : "fmt::@976f4f0bee90b99ecdb6",
					"jsonFile" : "target-fmt-Debug-c498a9ca8008b3b7d73f.json",
					"name" : "fmt",
					"projectIndex" : 1
				}
			]
		}
	],
	"kind" : "codemodel",
	"paths" : 
	{
		"build" : "D:/Users/PERSONAL/CLionProjects/FinalStudyMpi/cmake-build-debug",
		"source" : "D:/Users/PERSONAL/CLionProjects/FinalStudyMpi"
	},
	"version" : 
	{
		"major" : 2,
		"minor" : 5
	}
}
